scitrix/__init__.py
scitrix-0.1.3.dist-info/LICENSE
scitrix-0.1.3.dist-info/METADATA
scitrix-0.1.3.dist-info/WHEEL
scitrix-0.1.3.dist-info/top_level.txt
scitrix-0.1.3.dist-info/RECORD
