Metadata-Version: 2.1
Name: scitrix
Version: 0.1.3
Summary: Module to create Matrix and use Matrix Functions.
Home-page: https://github.com/PrakEntech/scitrix
Author: Prakhar Srivastava
Author-email: <prakhartech983@gmail.com>
Keywords: python,matrix,determinant,adjoint,functions
Classifier: Topic :: Scientific/Engineering :: Mathematics
Classifier: Development Status :: 5 - Production/Stable
Classifier: Intended Audience :: Developers
Classifier: Programming Language :: Python :: 3.5
Classifier: Programming Language :: Python :: 3.6
Classifier: Programming Language :: Python :: 3 :: Only
Classifier: Operating System :: Unix
Classifier: Operating System :: MacOS :: MacOS X
Classifier: Operating System :: Microsoft :: Windows
License-File: LICENSE
Requires-Dist: tabulate
